[
  {
    "id": "cfcbadba-f5b5-4eea-9092-0f667c134a24",
    "data": [
      {
        "text": "I\u0027m angry",
        "userDefined": false
      }
    ],
    "isTemplate": false,
    "count": 0,
    "updated": 0
  },
  {
    "id": "4c45fa3c-2749-4536-8b56-3dda711c8275",
    "data": [
      {
        "text": "I am mad",
        "userDefined": false
      }
    ],
    "isTemplate": false,
    "count": 0,
    "updated": 0
  },
  {
    "id": "bd7219e3-2050-4092-a994-bb605d8aae9d",
    "data": [
      {
        "text": "I\u0027m furious",
        "userDefined": false
      }
    ],
    "isTemplate": false,
    "count": 0,
    "updated": 0
  },
  {
    "id": "d696d3d0-216f-4c6a-b13a-3bb9d8084ca0",
    "data": [
      {
        "text": "I am mad at you",
        "userDefined": false
      }
    ],
    "isTemplate": false,
    "count": 0,
    "updated": 0
  },
  {
    "id": "19c32ab3-3f61-4e82-b635-a093057f44ab",
    "data": [
      {
        "text": "I\u0027",
        "userDefined": false
      },
      {
        "text": "m",
        "meta": "@sys.ignore",
        "userDefined": false
      },
      {
        "text": " enraged",
        "userDefined": false
      }
    ],
    "isTemplate": false,
    "count": 0,
    "updated": 0
  },
  {
    "id": "da41203c-357e-46d6-9ec7-940c9047649c",
    "data": [
      {
        "text": "I\u0027m being mad",
        "userDefined": false
      }
    ],
    "isTemplate": false,
    "count": 0,
    "updated": 0
  },
  {
    "id": "698a4cae-334e-4170-9c6d-1ee06cdf7212",
    "data": [
      {
        "text": "I am angry with you",
        "userDefined": false
      }
    ],
    "isTemplate": false,
    "count": 0,
    "updated": 0
  }
]